imagesplit/__init__.py
imagesplit/__main__.py
imagesplit/applications/__init__.py
imagesplit/applications/split_files.py
imagesplit/applications/write_files.py
imagesplit/file/__init__.py
imagesplit/file/data_type.py
imagesplit/file/file_factory.py
imagesplit/file/file_formats.py
imagesplit/file/file_image_descriptor.py
imagesplit/file/file_wrapper.py
imagesplit/file/format_factory.py
imagesplit/file/image_file_reader.py
imagesplit/file/metaio_reader.py
imagesplit/file/tiff_file_reader.py
imagesplit/file/vol_reader.py
imagesplit/image/__init__.py
imagesplit/image/combined_image.py
imagesplit/image/image_wrapper.py
imagesplit/utils/__init__.py
imagesplit/utils/file_descriptor.py
imagesplit/utils/json_reader.py
imagesplit/utils/utilities.py
imagesplit/utils/versioneer_version.py
imagesplit/utils/versioning.py
ImageSplit-0.3.4.dist-info/LICENSE
ImageSplit-0.3.4.dist-info/METADATA
ImageSplit-0.3.4.dist-info/WHEEL
ImageSplit-0.3.4.dist-info/entry_points.txt
ImageSplit-0.3.4.dist-info/top_level.txt
ImageSplit-0.3.4.dist-info/RECORD
